statstests/__init__.py
statstests/process.py
statstests/tests.py
statstests/datasets/__init__.py
statstests/datasets/util.py
statstests/datasets/bebes/__init__.py
statstests/datasets/bebes/bebes.csv
statstests/datasets/corruption/__init__.py
statstests/datasets/corruption/corruption.csv
statstests/datasets/empresas/__init__.py
statstests/datasets/empresas/empresas.csv
statstests-1.0.8.dist-info/AUTHORS
statstests-1.0.8.dist-info/LICENSE.txt
statstests-1.0.8.dist-info/METADATA
statstests-1.0.8.dist-info/WHEEL
statstests-1.0.8.dist-info/pbr.json
statstests-1.0.8.dist-info/top_level.txt
statstests-1.0.8.dist-info/RECORD
