Metadata-Version: 2.1
Name: statstests
Version: 1.0.8
Summary: UNKNOWN
Home-page: UNKNOWN
Author: Helder Prado Santos, Luiz Paulo Fávero
Author-email: pystatstests@gmail.com
License: MIT
Project-URL: Source Code, https://github.com/stats-tests/statstests
Keywords: statstests, statsmodels, statistical tests, statistical process
Platform: UNKNOWN
Classifier: Development Status :: 4 - Beta
Classifier: Environment :: Console
Classifier: Intended Audience :: Developers
Classifier: Intended Audience :: Information Technology
Classifier: Operating System :: Microsoft :: Windows
Classifier: Programming Language :: Python :: 3.3
Classifier: Programming Language :: Python :: 3.4
Classifier: Programming Language :: Python :: 3.5
Classifier: Programming Language :: Python :: 3.6
Classifier: Programming Language :: Python :: 3.7
Classifier: Programming Language :: Python :: 3.8
Classifier: Programming Language :: Python :: 3.9
License-File: LICENSE.txt
License-File: AUTHORS
